find_exe/__init__.py
find_exe/__main__.py
find_exe/_core.py
find_exe/cli.py
find_exe/py.typed
find_exe-0.2.1.dist-info/METADATA
find_exe-0.2.1.dist-info/WHEEL
find_exe-0.2.1.dist-info/entry_points.txt
find_exe-0.2.1.dist-info/licenses/LICENSE.txt
find_exe-0.2.1.dist-info/RECORD
