Metadata-Version: 2.3
Name: find-exe
Version: 0.2.1
Summary: Find matching executables
Project-URL: Homepage, https://ofek.dev/find-exe/
Project-URL: Sponsor, https://github.com/sponsors/ofek
Project-URL: Changelog, https://ofek.dev/find-exe/changelog/
Project-URL: Tracker, https://github.com/ofek/find-exe/issues
Project-URL: Source, https://github.com/ofek/find-exe
Author-email: Ofek Lev <oss@ofek.dev>
License-Expression: MIT
License-File: LICENSE.txt
Keywords: binary,cli,executable,path,which
Classifier: Development Status :: 4 - Beta
Classifier: Programming Language :: Python
Classifier: Programming Language :: Python :: 3.8
Classifier: Programming Language :: Python :: 3.9
Classifier: Programming Language :: Python :: 3.10
Classifier: Programming Language :: Python :: 3.11
Classifier: Programming Language :: Python :: 3.12
Classifier: Programming Language :: Python :: 3.13
Classifier: Programming Language :: Python :: Implementation :: CPython
Classifier: Programming Language :: Python :: Implementation :: PyPy
Requires-Python: >=3.8
